keybird/__init__.py
keybird/deploy_cli.py
keybird/server.py
keybird/setup.py
keybird/uninstall.py
keybird/scripts/cleanup_gadget.sh
keybird/scripts/gadget.conf
keybird/scripts/setup_gadget.sh
keybird/scripts/setup_gadget_composite.sh
keybird/static/android-icon-144x144.png
keybird/static/android-icon-192x192.png
keybird/static/android-icon-36x36.png
keybird/static/android-icon-48x48.png
keybird/static/android-icon-72x72.png
keybird/static/android-icon-96x96.png
keybird/static/apple-icon-114x114.png
keybird/static/apple-icon-120x120.png
keybird/static/apple-icon-144x144.png
keybird/static/apple-icon-152x152.png
keybird/static/apple-icon-180x180.png
keybird/static/apple-icon-57x57.png
keybird/static/apple-icon-60x60.png
keybird/static/apple-icon-72x72.png
keybird/static/apple-icon-76x76.png
keybird/static/apple-icon-precomposed.png
keybird/static/apple-icon.png
keybird/static/browserconfig.xml
keybird/static/favicon-16x16.png
keybird/static/favicon-32x32.png
keybird/static/favicon-96x96.png
keybird/static/favicon.ico
keybird/static/manifest.json
keybird/static/ms-icon-144x144.png
keybird/static/ms-icon-150x150.png
keybird/static/ms-icon-310x310.png
keybird/static/ms-icon-70x70.png
keybird/static/css/style.css
keybird/static/js/app.js
keybird/systemd/hid-gadget.service
keybird/systemd/pi-hid-bridge.service
keybird/templates/index.html
keybird-1.0.12.dist-info/licenses/LICENSE
keybird-1.0.12.dist-info/METADATA
keybird-1.0.12.dist-info/WHEEL
keybird-1.0.12.dist-info/entry_points.txt
keybird-1.0.12.dist-info/top_level.txt
keybird-1.0.12.dist-info/RECORD
