Metadata-Version: 2.4
Name: keybird
Version: 1.0.12
Summary: Turn a Raspberry Pi into a USB HID keyboard/mouse bridge with web-based control
Author-email: Ian McCutcheon <ian@mcyork.com>
License-Expression: MIT
Project-URL: Homepage, https://github.com/mcyork/keybird
Project-URL: Repository, https://github.com/mcyork/keybird
Project-URL: Issues, https://github.com/mcyork/keybird/issues
Keywords: raspberry-pi,hid,usb-gadget,keyboard,mouse,kvm
Classifier: Development Status :: 4 - Beta
Classifier: Intended Audience :: System Administrators
Classifier: Intended Audience :: Developers
Classifier: Operating System :: POSIX :: Linux
Classifier: Programming Language :: Python :: 3
Classifier: Programming Language :: Python :: 3.10
Classifier: Programming Language :: Python :: 3.11
Classifier: Programming Language :: Python :: 3.12
Classifier: Topic :: System :: Hardware
Classifier: Topic :: System :: Networking
Requires-Python: >=3.10
License-File: LICENSE
Requires-Dist: flask>=2.0.0
Provides-Extra: dev
Requires-Dist: pytest>=7.0; extra == "dev"
Requires-Dist: black>=22.0; extra == "dev"
Dynamic: license-file
